setup.py
Topsis_Anmol_101917136.egg-info/PKG-INFO
Topsis_Anmol_101917136.egg-info/SOURCES.txt
Topsis_Anmol_101917136.egg-info/dependency_links.txt
Topsis_Anmol_101917136.egg-info/entry_points.txt
Topsis_Anmol_101917136.egg-info/requires.txt
Topsis_Anmol_101917136.egg-info/top_level.txt
topsis/__init__.py
topsis/topsis.py