Metadata-Version: 2.1
Name: Topsis-Anmol-101917136
Version: 0.1
Summary: A Python package implementing TOPSIS technique.
Home-page: UNKNOWN
Author: Anmol Tiwari
Author-email: atiwari4_be19@thapar.edu
License: MIT
Platform: UNKNOWN
Classifier: License :: OSI Approved :: MIT License
Classifier: Programming Language :: Python :: 3
Classifier: Programming Language :: Python :: 3.7
